Metadata-Version: 2.1
Name: ConversorBR
Version: 0.0.1
Summary: Converter mediadas usadas nos estados Unidos para medidas usadas no Brasil 
Home-page: https://github.com/RNNSNTS/ConversorBR
Author: RNNSMP
Author-email: renansampaio@id.uff.br
License: UNKNOWN
Platform: UNKNOWN
Requires-Python: >=3.8
License-File: LICENSE.txt
